inat2wiki/__init__.py
inat2wiki/cli.py
inat2wiki/get_user_observations.py
inat2wiki/inat_taxon2wikidata.py
inat2wiki/parse_observation.py
inat2wiki-0.0.5.dist-info/licenses/LICENSE
inat2wiki-0.0.5.dist-info/METADATA
inat2wiki-0.0.5.dist-info/WHEEL
inat2wiki-0.0.5.dist-info/entry_points.txt
inat2wiki-0.0.5.dist-info/top_level.txt
inat2wiki-0.0.5.dist-info/RECORD
